envlint/__init__.py
envlint/cli.py
envlint/parser.py
envlint/schema.py
envlint/validator.py
envlint-0.1.0.dist-info/METADATA
envlint-0.1.0.dist-info/WHEEL
envlint-0.1.0.dist-info/entry_points.txt
envlint-0.1.0.dist-info/licenses/LICENSE
envlint-0.1.0.dist-info/RECORD
