Metadata-Version: 2.4
Name: envlint
Version: 0.1.0
Summary: Validate .env files against a schema. Catch missing and invalid environment variables before runtime.
Project-URL: Homepage, https://github.com/cainky/envlint
Project-URL: Repository, https://github.com/cainky/envlint
Project-URL: Issues, https://github.com/cainky/envlint/issues
Author-email: Kyle Cain <kyle@kylecain.me>
License-Expression: GPL-3.0-or-later
License-File: LICENSE
Keywords: ci-cd,cli,devops,dotenv,env,environment,schema,validation
Classifier: Development Status :: 4 - Beta
Classifier: Environment :: Console
Classifier: Intended Audience :: Developers
Classifier: License :: OSI Approved :: GNU General Public License v3 (GPLv3)
Classifier: Operating System :: OS Independent
Classifier: Programming Language :: Python :: 3
Classifier: Programming Language :: Python :: 3.9
Classifier: Programming Language :: Python :: 3.10
Classifier: Programming Language :: Python :: 3.11
Classifier: Programming Language :: Python :: 3.12
Classifier: Topic :: Software Development :: Quality Assurance
Classifier: Topic :: Software Development :: Testing
Classifier: Topic :: System :: Systems Administration
Requires-Python: >=3.9
Requires-Dist: pyyaml>=6.0
Requires-Dist: rich>=13.0.0
Requires-Dist: typer>=0.9.0
Provides-Extra: dev
Requires-Dist: pytest-cov>=4.0.0; extra == 'dev'
Requires-Dist: pytest>=7.0.0; extra == 'dev'
Requires-Dist: ruff>=0.1.0; extra == 'dev'
